dynamic_expressions/__init__.py
dynamic_expressions/dispatcher.py
dynamic_expressions/extensions.py
dynamic_expressions/middlewares.py
dynamic_expressions/nodes.py
dynamic_expressions/py.typed
dynamic_expressions/types.py
dynamic_expressions/visitors.py
dynamic_expressions/cache/__init__.py
dynamic_expressions/cache/base.py
dynamic_expressions/cache/redis.py
dynamic_expressions/serialization/__init__.py
dynamic_expressions/serialization/_serialization.py
dynamic_expressions/serialization/msgspec.py
dynamic_expressions/serialization/pydantic.py
dynamic_expressions-0.2.1.dist-info/METADATA
dynamic_expressions-0.2.1.dist-info/WHEEL
dynamic_expressions-0.2.1.dist-info/top_level.txt
dynamic_expressions-0.2.1.dist-info/RECORD
